tap_procore/__init__.py
tap_procore/streams.py
tap_procore/tap.py
tap_procore/tests/__init__.py
tap_procore/tests/test_core.py
tap_procore-0.0.5.dist-info/entry_points.txt
tap_procore-0.0.5.dist-info/WHEEL
tap_procore-0.0.5.dist-info/METADATA
tap_procore-0.0.5.dist-info/RECORD
