Metadata-Version: 2.1
Name: tap-procore
Version: 0.0.5
Summary: `tap-procore` is Singer tap for procore, built with the Singer SDK.
License: Apache 2.0
Author: hotglue
Requires-Python: >=3.6,<3.9
Classifier: License :: Other/Proprietary License
Classifier: Programming Language :: Python :: 3
Classifier: Programming Language :: Python :: 3.6
Classifier: Programming Language :: Python :: 3.7
Classifier: Programming Language :: Python :: 3.8
Requires-Dist: requests (>=2.25.1,<3.0.0)
Requires-Dist: singer-sdk (>=0.1.0,<0.2.0)
